README.md
setup.py
privatebroker/__init__.py
privatebroker/exceptions.py
privatebroker/privatebroker.py
privatebroker.egg-info/PKG-INFO
privatebroker.egg-info/SOURCES.txt
privatebroker.egg-info/dependency_links.txt
privatebroker.egg-info/not-zip-safe
privatebroker.egg-info/top_level.txt